{
  "carouselItems": [
    {
      "imageResource": "xxx",
      "url": "XXX",
      "title": "Item 1",
      "position": 1
    },
    {
      "imageResource": "XXX",
      "url": "XXX",
      "title": "Item 2",
      "position": 2
    },
    {
      "imageResource": "XXX",
      "url": "",
      "title": "Item 3",
      "position": 3
    }
  ],
  "services" : [
    {
      "title": "GUNET",
      "imageUrl": "https://www.cs.unipi.gr/media/k2/items/cache/6cff81ed2fd5fd02c6bfe5986e55231b_XS.jpg",
      "url" : "https://gunet2.cs.unipi.gr/"
    },
    {
      "title": "Ηλεκτρονική Γραμματεία",
      "imageUrl": "https://www.cs.unipi.gr/media/k2/items/cache/0b1ad7a7b79268a1f4558db78e092446_XS.jpg",
      "url" : "https://students.unipi.gr"
    },
    {
      "title": "CSLab",
      "imageUrl": "https://www.cs.unipi.gr/media/k2/items/cache/2722f6bcd13027c06fe9d3b0e6f955cf_XS.jpg",
      "url" : "https://cslab.unipi.gr/"
    },
    {
      "title": "Βιβλιοθήκη",
      "imageUrl": "https://www.cs.unipi.gr/media/k2/items/cache/f0ba2bfd8f936a77d3b146acfe9443c7_XS.jpg",
      "url" : "https://www.lib.unipi.gr/iguana/www.main.cls?surl=library"
    },
    {
      "title": "ΕΥΔΟΞΟΣ",
      "imageUrl": "https://www.cs.unipi.gr/media/k2/items/cache/b1d237aad44a95e3871fc116e6241517_XS.jpg",
      "url" : "https://eudoxus.gr/"
    },
    {
      "title": "Helpdesk",
      "imageUrl": "https://www.cs.unipi.gr/media/k2/items/cache/e2acd849d365015ef08ef5b696dc9e31_XS.jpg",
      "url" : "https://helpdesk.unipi.gr/"
    },
    {
      "title": "ΚΕΠΠ",
      "imageUrl": "https://www.cs.unipi.gr/media/k2/items/cache/5288462d048e0d3f60f64bb84cff6df4_XS.jpg",
      "url" : "http://www.kep.unipi.gr/"
    },
    {
      "title": "UNIPI",
      "imageUrl": "https://www.cs.unipi.gr/media/k2/items/cache/b262fcb3a88d76445a5d5d6ad933cf2d_XS.jpg",
      "url" : "https://www.unipi.gr/unipi/el/"
    },
    {
      "title": "Γρ. Διασύνδεσης",
      "imageUrl": "https://www.cs.unipi.gr/media/k2/items/cache/bc5983b67a44bcede801e2ff363b54e0_XS.jpg",
      "url" : "https://career.unipi.gr/"
    }
  ]
}